{"continue": {"iistart": "2009-06-11T11:59:05Z", "continue": "||"}, "query": {"pages": {"736454": {"pageid": 736454, "ns": 6, "title": "File:GClef.svg", "imagerepository": "local", "imageinfo": [{"size": 1959, "width": 15, "height": 41, "canonicaltitle": "File:GClef.svg", "url": "https://upload.wikimedia.org/wikipedia/commons/f/ff/GClef.svg", "descriptionurl": "https://commons.wikimedia.org/wiki/File:GClef.svg", "descriptionshorturl": "https://commons.wikimedia.org/w/index.php?curid=736454", "extmetadata": {"DateTime": {"value": "2012-10-02 09:34:12", "source": "mediawiki-metadata", "hidden": ""}, "ObjectName": {"value": "GClef", "source": "mediawiki-metadata"}, "CommonsMetadataExtension": {"value": 1.2, "source": "extension", "hidden": ""}, "Categories": {"value": "PD ineligible|G clef|Musical score components|Valid SVG created with Text Editor|Template:Music", "source": "commons-categories", "hidden": ""}, "Assessments": {"value": "", "source": "commons-categories", "hidden": ""}, "ImageDescription": {"value": "G clef; one of <a href=\"//commons.wikimedia.org/wiki/Category:Musical_score_components\" title=\"Category:Musical score components\">Musical score components</a>", "source": "commons-desc-page"}, "DateTimeOriginal": {"value": "2006-04-27", "source": "commons-desc-page"}, "Credit": {"value": "<span class=\"int-own-work\" lang=\"en\">Own work</span>", "source": "commons-desc-page"}, "Artist": {"value": "<a href=\"//commons.wikimedia.org/wiki/User:%E3%81%A3\" title=\"User:っ\">っ</a>", "source": "commons-desc-page"}, "LicenseShortName": {"value": "Public domain", "source": "commons-desc-page", "hidden": ""}, "UsageTerms": {"value": "Public domain", "source": "commons-desc-page"}, "AttributionRequired": {"value": "false", "source": "commons-desc-page", "hidden": ""}, "Copyrighted": {"value": "False", "source": "commons-desc-page", "hidden": ""}, "Restrictions": {"value": "", "source": "commons-desc-page", "hidden": ""}, "License": {"value": "pd", "source": "commons-templates", "hidden": ""}}, "mime": "image/svg+xml"}]}}}}