{"entities": {"Q77062": {"pageid": 79660, "ns": 0, "title": "Q77062", "lastrevid": 2455995320, "modified": "2026-01-19T02:34:22Z", "type": "item", "id": "Q77062", "labels": {"lb": {"language": "lb", "value": "Mandarinfësch"}, "zh": {"language": "zh", "value": "花斑連鰭䲗"}, "pl": {"language": "pl", "value": "Mandaryn wspaniały"}, "bs": {"language": "bs", "value": "Mandarinka"}, "he": {"language": "he", "value": "מנדרין"}, "es": {"language": "es", "value": "Synchiropus splendidus"}, "hu": {"language": "hu", "value": "mandarinhal"}, "it": {"language": "it", "value": "Synchiropus splendidus"}, "gl": {"language": "gl", "value": "Peixe mandarín"}, "de": {"language": "de", "value": "Mandarinfisch"}, "id": {"language": "id", "value": "Ikan mandarin"}, "ja": {"language": "ja", "value": "ニシキテグリ"}, "vi": {"language": "vi", "value": "Cá trạng nguyên"}, "pnb": {"language": "pnb", "value": "مینڈارن مچھی"}, "nl": {"language": "nl", "value": "blauwe mandarijn pitvis"}, "pt": {"language": "pt", "value": "Mandarim-real"}, "eo": {"language": "eo", "value": "Mandarena fiŝo"}, "ru": {"language": "ru", "value": "Мандаринка"}, "en": {"language": "en", "value": "Mandarinfish"}, "tr": {"language": "tr", "value": "Mandalina balığı"}, "th": {"language": "th", "value": "ปลาแมนดาริน"}, "ca": {"language": "ca", "value": "peix mandarí"}, "fi": {"language": "fi", "value": "mandariinikala"}, "uk": {"language": "uk", "value": "Мандаринка"}, "cs": {"language": "cs", "value": "vřeténka mandarín"}, "fa": {"language": "fa", "value": "ماهی ماندارین"}, "bg": {"language": "bg", "value": "риба мандарин"}, "az": {"language": "az", "value": "Mandarinka"}, "fr": {"language": "fr", "value": "Synchiropus splendidus"}, "sv": {"language": "sv", "value": "Synchiropus splendidus"}, "diq": {"language": "diq", "value": "Maseyê mandalina"}, "la": {"language": "la", "value": "Synchiropus splendidus"}, "ar": {"language": "ar", "value": "سمك مندرين"}, "hy": {"language": "hy", "value": "մանդարինկա"}, "br": {"language": "br", "value": "Synchiropus splendidus"}, "ia": {"language": "ia", "value": "Synchiropus splendidus"}, "hr": {"language": "hr", "value": "Mandarinska riba"}, "ko": {"language": "ko", "value": "만다린피시"}, "zh-tw": {"language": "zh-tw", "value": "花斑連鰭䲗"}, "eu": {"language": "eu", "value": "Synchiropus splendidus"}, "ky": {"language": "ky", "value": "Мандаринбалык"}, "ast": {"language": "ast", "value": "Synchiropus splendidus"}, "ga": {"language": "ga", "value": "Synchiropus splendidus"}, "ro": {"language": "ro", "value": "Synchiropus splendidus"}, "sq": {"language": "sq", "value": "Synchiropus splendidus"}, "ceb": {"language": "ceb", "value": "Synchiropus splendidus"}, "war": {"language": "war", "value": "Synchiropus splendidus"}, "arz": {"language": "arz", "value": "سمك ماندارين"}, "be-tarask": {"language": "be-tarask", "value": "мандарынка"}, "af": {"language": "af", "value": "Mandarynvis"}, "mul": {"language": "mul", "value": "Synchiropus splendidus"}}, "descriptions": {"it": {"language": "it", "value": "specie di pesce"}, "de": {"language": "de", "value": "Art der Gattung Synchiropus"}, "fr": {"language": "fr", "value": "espèce de poissons"}, "en": {"language": "en", "value": "fish species of western Pacific Ocean"}, "bg": {"language": "bg", "value": "вид риба"}, "nl": {"language": "nl", "value": "straalvinnige vissensoort uit de familie pitvissen"}, "fi": {"language": "fi", "value": "kalalaji"}, "ar": {"language": "ar", "value": "نوع من الأسماك"}, "sq": {"language": "sq", "value": "lloj i peshqve"}, "uk": {"language": "uk", "value": "вид риб"}, "ja": {"language": "ja", "value": "魚の種類"}, "ast": {"language": "ast", "value": "especie de pexe"}, "ga": {"language": "ga", "value": "speiceas iasc"}, "pt": {"language": "pt", "value": "espécie de peixe"}, "arz": {"language": "arz", "value": "نوع من الاسماك"}, "sv": {"language": "sv", "value": "fiskart"}, "cs": {"language": "cs", "value": "Druh ryby"}, "pl": {"language": "pl", "value": "gatunek ryb z rodziny lirowatych"}, "hu": {"language": "hu", "value": "halfaj"}, "be-tarask": {"language": "be-tarask", "value": "від рыбаў"}, "ca": {"language": "ca", "value": "espècie de peix"}, "es": {"language": "es", "value": "especie de peces"}, "ko": {"language": "ko", "value": "농어목 돛양태과의 바닷물고기"}, "af": {"language": "af", "value": "visspesie van westelike Stille Oseaan"}}, "aliases": {"zh": [{"language": "zh", "value": "皇冠青蛙"}, {"language": "zh", "value": "五彩青蛙"}, {"language": "zh", "value": "綠青蛙"}, {"language": "zh", "value": "七彩麒麟"}, {"language": "zh", "value": "花斑连鳍䲗"}, {"language": "zh", "value": "綠麒麟"}], "pl": [{"language": "pl", "value": "Synchiropus splendidus"}], "fr": [{"language": "fr", "value": "Poisson-mandarin"}, {"language": "fr", "value": "Poisson cachemire"}, {"language": "fr", "value": "Gobie mandarin"}, {"language": "fr", "value": "Pterosynchiropus splendidus"}], "bs": [{"language": "bs", "value": "Synchiropus splendidus"}], "he": [{"language": "he", "value": "שפריר מקושט"}, {"language": "he", "value": "שפרירנון הודי"}], "de": [{"language": "de", "value": "Synchiropus splendidus"}, {"language": "de", "value": "Mandarin-Leierfisch"}], "ja": [{"language": "ja", "value": "錦手繰"}, {"language": "ja", "value": "マンダリンフィッシュ"}], "vi": [{"language": "vi", "value": "Synchiropus splendidus"}], "nl": [{"language": "nl", "value": "Synchiropus splendidus"}, {"language": "nl", "value": "Mandarinska riba"}], "pt": [{"language": "pt", "value": "Synchiropus splendidus"}, {"language": "pt", "value": "Peixe mandarim"}], "ru": [{"language": "ru", "value": "Бычковая мандаринка"}, {"language": "ru", "value": "Synchiropus splendidus"}], "tr": [{"language": "tr", "value": "Synchiropus splendidus"}, {"language": "tr", "value": "Mandalinabalığı"}, {"language": "tr", "value": "Pterosynchiropus splendidus"}], "th": [{"language": "th", "value": "Synchiropus splendidus"}], "ca": [{"language": "ca", "value": "Synchiropus splendidus"}], "fi": [{"language": "fi", "value": "Synchiropus splendidus"}, {"language": "fi", "value": "Pterosynchiropus splendidus"}], "uk": [{"language": "uk", "value": "Synchiropus splendidus"}], "cs": [{"language": "cs", "value": "Synchiropus splendidus"}, {"language": "cs", "value": "Mandarín nádherný"}], "bg": [{"language": "bg", "value": "Synchiropus splendidus"}, {"language": "bg", "value": "Callionymus splendidus"}], "az": [{"language": "az", "value": "Pterosinonimchiropus splendidus"}, {"language": "az", "value": "Synchiropus splendidus"}, {"language": "az", "value": "Neosinonimchiropus splendidus"}, {"language": "az", "value": "Callionymus splendidus"}], "en": [{"language": "en", "value": "Synchiropus splendidus"}], "zh-tw": [{"language": "zh-tw", "value": "老鼠"}, {"language": "zh-tw", "value": "狗圻"}, {"language": "zh-tw", "value": "青蛙"}], "ast": [{"language": "ast", "value": "Pexe mandarín"}, {"language": "ast", "value": "pexe mandarín"}], "be-tarask": [{"language": "be-tarask", "value": "Synchiropus splendidus"}], "ar": [{"language": "ar", "value": "سمك ماندارين"}]}, "claims": {"P373": [{"mainsnak": {"snaktype": "value", "property": "P373", "hash": "2e731c7537e6e075e74acddd26a9e3a9a1d2c354", "datavalue": {"value": "Synchiropus splendidus", "type": "string"}, "datatype": "string"}, "type": "statement", "id": "q77062$2A180442-81DC-4541-8E28-2BEF3C729A30", "rank": "normal"}], "P105": [{"mainsnak": {"snaktype": "value", "property": "P105", "hash": "aebf3611b23ed90c7c0fc80f6cd1cb7be110ea59", "datavalue": {"value": {"entity-type": "item", "numeric-id": 7432, "id": "Q7432"}, "type": "wikibase-entityid"}, "datatype": "wikibase-item"}, "type": "statement", "id": "q77062$DEF1174A-DDF1-4E46-962C-19CE6ED239D2", "rank": "normal", "references": [{"hash": "89e96b63b05055cc80c950cf5fea109c7d453658", "snaks": {"P248": [{"snaktype": "value", "property": "P248", "hash": "c26dbcef1202a7d198982ed24f6ea69b704f95fe", "datavalue": {"value": {"entity-type": "item", "numeric-id": 82575, "id": "Q82575"}, "type": "wikibase-entityid"}, "datatype": "wikibase-item"}], "P577": [{"snaktype": "value", "property": "P577", "hash": "539fa499b6ea982e64006270bb26f52a57a8e32b", "datavalue": {"value": {"time": "+1996-06-13T00:00:00Z", "timezone": 0, "before": 0, "after": 0, "precision": 11, "calendarmodel": "http://www.wikidata.org/entity/Q1985727"}, "type": "time"}, "datatype": "time"}], "P813": [{"snaktype": "value", "property": "P813", "hash": "96dfb8481e184edb40553947f8fe08ce080f1553", "datavalue": {"value": {"time": "+2013-09-19T00:00:00Z", "timezone": 0, "before": 0, "after": 0, "precision": 11, "calendarmodel": "http://www.wikidata.org/entity/Q1985727"}, "type": "time"}, "datatype": "time"}]}, "snaks-order": ["P248", "P577", "P813"]}]}], "P225": [{"mainsnak": {"snaktype": "value", "property": "P225", "hash": "31e79cf0bafd48f58e6d6e6d78711d6222df925a", "datavalue": {"value": "Synchiropus splendidus", "type": "string"}, "datatype": "string"}, "type": "statement", "qualifiers": {"P405": [{"snaktype": "value", "property": "P405", "hash": "b79ffd94bd5ad2028efa0ae94a7528e250020735", "datavalue": {"value": {"entity-type": "item", "numeric-id": 425571, "id": "Q425571"}, "type": "wikibase-entityid"}, "datatype": "wikibase-item"}], "P574": [{"snaktype": "value", "property": "P574", "hash": "4a3ff9f4266522cfb345294258b8f0724ac29247", "datavalue": {"value": {"time": "+1927-01-01T00:00:00Z", "timezone": 0, "before": 0, "after": 0, "precision": 9, "calendarmodel": "http://www.wikidata.org/entity/Q1985727"}, "type": "time"}, "datatype": "time"}]}, "qualifiers-order": ["P405", "P574"], "id": "q77062$184E4733-6D67-4C1B-A78F-01D3DC22CEC2", "rank": "normal", "references": [{"hash": "89e96b63b05055cc80c950cf5fea109c7d453658", "snaks": {"P248": [{"snaktype": "value", "property": "P248", "hash": "c26dbcef1202a7d198982ed24f6ea69b704f95fe", "datavalue": {"value": {"entity-type": "item", "numeric-id": 82575, "id": "Q82575"}, "type": "wikibase-entityid"}, "datatype": "wikibase-item"}], "P577": [{"snaktype": "value", "property": "P577", "hash": "539fa499b6ea982e64006270bb26f52a57a8e32b", "datavalue": {"value": {"time": "+1996-06-13T00:00:00Z", "timezone": 0, "before": 0, "after": 0, "precision": 11, "calendarmodel": "http://www.wikidata.org/entity/Q1985727"}, "type": "time"}, "datatype": "time"}], "P813": [{"snaktype": "value", "property": "P813", "hash": "96dfb8481e184edb40553947f8fe08ce080f1553", "datavalue": {"value": {"time": "+2013-09-19T00:00:00Z", "timezone": 0, "before": 0, "after": 0, "precision": 11, "calendarmodel": "http://www.wikidata.org/entity/Q1985727"}, "type": "time"}, "datatype": "time"}]}, "snaks-order": ["P248", "P577", "P813"]}]}], "P18": [{"mainsnak": {"snaktype": "value", "property": "P18", "hash": "904e2919c0a41a35e508d599e4773460e0edac1a", "datavalue": {"value": "Synchiropus splendidus 2 Luc Viatour.jpg", "type": "string"}, "datatype": "commonsMedia"}, "type": "statement", "qualifiers": {"P21": [{"snaktype": "value", "property": "P21", "hash": "0576a008261e5b2544d1ff3328c94bd529379536", "datavalue": {"value": {"entity-type": "item", "numeric-id": 44148, "id": "Q44148"}, "type": "wikibase-entityid"}, "datatype": "wikibase-item"}]}, "qualifiers-order": ["P21"], "id": "q77062$01400A7D-362A-4FC9-8DE8-EFDBD2B9D598", "rank": "normal"}, {"mainsnak": {"snaktype": "value", "property": "P18", "hash": "4e7a1e4b82b18dd891986a676b2bd3ac5b57add8", "datavalue": {"value": "Synchiropus splendidus 02.JPG", "type": "string"}, "datatype": "commonsMedia"}, "type": "statement", "qualifiers": {"P21": [{"snaktype": "value", "property": "P21", "hash": "a274865baccd3ff04c28d5ffdcc12e0079f5a201", "datavalue": {"value": {"entity-type": "item", "numeric-id": 43445, "id": "Q43445"}, "type": "wikibase-entityid"}, "datatype": "wikibase-item"}]}, "qualifiers-order": ["P21"], "id": "Q77062$325433E3-C4DE-4678-8274-F364452CF118", "rank": "normal"}], "P815": [{"mainsnak": {"snaktype": "value", "property": "P815", "hash": "c36da02f5b0d1bbf6622c448543486d44c7095e2", "datavalue": {"value": "171730", "type": "string"}, "datatype": "external-id"}, "type": "statement", "id": "Q77062$4C2968F8-CF1F-4DBB-BC89-FF51E5825AAA", "rank": "normal", "references": [{"hash": "84b0bc804cd5367055bc5aac1e339b807ff3ad3f", "snaks": {"P248": [{"snaktype": "value", "property": "P248", "hash": "c26dbcef1202a7d198982ed24f6ea69b704f95fe", "datavalue": {"value": {"entity-type": "item", "numeric-id": 82575, "id": "Q82575"}, "type": "wikibase-entityid"}, "datatype": "wikibase-item"}], "P813": [{"snaktype": "value", "property": "P813", "hash": "68f921417b456e3a6e13524eec6d7559c21ffbad", "datavalue": {"value": {"time": "+2014-11-05T00:00:00Z", "timezone": 0, "before": 0, "after": 0, "precision": 11, "calendarmodel": "http://www.wikidata.org/entity/Q1985727"}, "type": "time"}, "datatype": "time"}]}, "snaks-order": ["P248", "P813"]}]}], "P646": [{"mainsnak": {"snaktype": "value", "property": "P646", "hash": "41032213e05487a91640fb6e0f1df9e221f6d605", "datavalue": {"value": "/m/09pqfp", "type": "string"}, "datatype": "external-id"}, "type": "statement", "id": "Q77062$C4150A4D-45DF-430B-98EB-8C1854242225", "rank": "normal", "references": [{"hash": "2b00cb481cddcac7623114367489b5c194901c4a", "snaks": {"P248": [{"snaktype": "value", "property": "P248", "hash": "a94b740202b097dd33355e0e6c00e54b9395e5e0", "datavalue": {"value": {"entity-type": "item", "numeric-id": 15241312, "id": "Q15241312"}, "type": "wikibase-entityid"}, "datatype": "wikibase-item"}], "P577": [{"snaktype": "value", "property": "P577", "hash": "fde79ecb015112d2f29229ccc1ec514ed3e71fa2", "datavalue": {"value": {"time": "+2013-10-28T00:00:00Z", "timezone": 0, "before": 0, "after": 0, "precision": 11, "calendarmodel": "http://www.wikidata.org/entity/Q1985727"}, "type": "time"}, "datatype": "time"}]}, "snaks-order": ["P248", "P577"]}]}], "P171": [{"mainsnak": {"snaktype": "value", "property": "P171", "hash": "3a2a2104895261d1bdd5c879ec67e06385e125d3", "datavalue": {"value": {"entity-type": "item", "numeric-id": 2684354, "id": "Q2684354"}, "type": "wikibase-entityid"}, "datatype": "wikibase-item"}, "type": "statement", "id": "Q77062$A2D7423B-CA4F-43F6-AEAB-0E4BB5552C18", "rank": "normal", "references": [{"hash": "fc9997808b8be45dcf9cd58e71dbd90f0ae755a5", "snaks": {"P248": [{"snaktype": "value", "property": "P248", "hash": "c26dbcef1202a7d198982ed24f6ea69b704f95fe", "datavalue": {"value": {"entity-type": "item", "numeric-id": 82575, "id": "Q82575"}, "type": "wikibase-entityid"}, "datatype": "wikibase-item"}], "P577": [{"snaktype": "value", "property": "P577", "hash": "539fa499b6ea982e64006270bb26f52a57a8e32b", "datavalue": {"value": {"time": "+1996-06-13T00:00:00Z", "timezone": 0, "before": 0, "after": 0, "precision": 11, "calendarmodel": "http://www.wikidata.org/entity/Q1985727"}, "type": "time"}, "datatype": "time"}], "P813": [{"snaktype": "value", "property": "P813", "hash": "08e80ae2ee0953bca6e1eddc18d104c990ec1884", "datavalue": {"value": {"time": "+2013-10-22T00:00:00Z", "timezone": 0, "before": 0, "after": 0, "precision": 11, "calendarmodel": "http://www.wikidata.org/entity/Q1985727"}, "type": "time"}, "datatype": "time"}]}, "snaks-order": ["P248", "P577", "P813"]}]}], "P31": [{"mainsnak": {"snaktype": "value", "property": "P31", "hash": "06629d890d7ab0ff85c403d8aadf57ce9809c01f", "datavalue": {"value": {"entity-type": "item", "numeric-id": 16521, "id": "Q16521"}, "type": "wikibase-entityid"}, "datatype": "wikibase-item"}, "type": "statement", "id": "Q77062$A018EE84-37EB-404A-8123-600A0C1D71E1", "rank": "normal"}], "P685": [{"mainsnak": {"snaktype": "value", "property": "P685", "hash": "72c2cf3b41284deb53878a966f622ccf0e112810", "datavalue": {"value": "270530", "type": "string"}, "datatype": "external-id"}, "type": "statement", "id": "Q77062$5C925AD2-0E9B-4F6D-AB06-ABE5CC00F284", "rank": "normal", "references": [{"hash": "288ab581e7d2d02995a26dfa8b091d96e78457fc", "snaks": {"P143": [{"snaktype": "value", "property": "P143", "hash": "6a164248fc96bfa583bbb495cb63ae6401ec203c", "datavalue": {"value": {"entity-type": "item", "numeric-id": 206855, "id": "Q206855"}, "type": "wikibase-entityid"}, "datatype": "wikibase-item"}]}, "snaks-order": ["P143"]}, {"hash": "2ecc417951972c44d6019f0d62ae5481d8bf5784", "snaks": {"P248": [{"snaktype": "value", "property": "P248", "hash": "97adcbd59494446fc2aa6489cab53e41e604243c", "datavalue": {"value": {"entity-type": "item", "numeric-id": 12159796, "id": "Q12159796"}, "type": "wikibase-entityid"}, "datatype": "wikibase-item"}], "P813": [{"snaktype": "value", "property": "P813", "hash": "041bc50ce29162a0366ac7946b4d65e042c07611", "datavalue": {"value": {"time": "+2019-06-25T00:00:00Z", "timezone": 0, "before": 0, "after": 0, "precision": 11, "calendarmodel": "http://www.wikidata.org/entity/Q1985727"}, "type": "time"}, "datatype": "time"}]}, "snaks-order": ["P248", "P813"]}]}], "P850": [{"mainsnak": {"snaktype": "value", "property": "P850", "hash": "717a0a9d16305f2b7b22ea49e76fae729097dafd", "datavalue": {"value": "273264", "type": "string"}, "datatype": "external-id"}, "type": "statement", "id": "Q77062$844A3F52-B1CE-4388-88D2-B7793BEBDD94", "rank": "normal", "references": [{"hash": "09de9acd3d9390b3ab4948b8ab9637a5dd932ea1", "snaks": {"P248": [{"snaktype": "value", "property": "P248", "hash": "c5517df7c2364e280b841bbd4cd538c720153d8c", "datavalue": {"value": {"entity-type": "item", "numeric-id": 604063, "id": "Q604063"}, "type": "wikibase-entityid"}, "datatype": "wikibase-item"}], "P813": [{"snaktype": "value", "property": "P813", "hash": "9e7acf9734c8cbf57b2544f908dbb74e20485ffa", "datavalue": {"value": {"time": "+2014-11-14T00:00:00Z", "timezone": 0, "before": 0, "after": 0, "precision": 11, "calendarmodel": "http://www.wikidata.org/entity/Q1985727"}, "type": "time"}, "datatype": "time"}]}, "snaks-order": ["P248", "P813"]}]}], "P938": [{"mainsnak": {"snaktype": "value", "property": "P938", "hash": "a54b278218830716e19240641d43e9295e40292e", "datavalue": {"value": "12644", "type": "string"}, "datatype": "external-id"}, "type": "statement", "id": "Q77062$C4F2C059-0C87-4672-ACD1-CD66858A1D1B", "rank": "normal", "references": [{"hash": "243737ae3e6c3c3f031f59324b4a40732d86b460", "snaks": {"P248": [{"snaktype": "value", "property": "P248", "hash": "5996fbd7847aa4bd2b7abe808fb9574e85fff2eb", "datavalue": {"value": {"entity-type": "item", "numeric-id": 837101, "id": "Q837101"}, "type": "wikibase-entityid"}, "datatype": "wikibase-item"}], "P813": [{"snaktype": "value", "property": "P813", "hash": "713383a751b8459976359db29307a866fa4f6aef", "datavalue": {"value": {"time": "+2015-05-21T00:00:00Z", "timezone": 0, "before": 0, "after": 0, "precision": 11, "calendarmodel": "http://www.wikidata.org/entity/Q1985727"}, "type": "time"}, "datatype": "time"}]}, "snaks-order": ["P248", "P813"]}]}], "P846": [{"mainsnak": {"snaktype": "value", "property": "P846", "hash": "e7cc9fbe9e179ea062f76a90092017352dbf8f0e", "datavalue": {"value": "2386640", "type": "string"}, "datatype": "external-id"}, "type": "statement", "id": "Q77062$E3A2D1E9-E3E7-46ED-BEFF-3EB08EC1BA22", "rank": "normal", "references": [{"hash": "b5ad2569bcf6622780b588eb1117c5be83d6a41a", "snaks": {"P248": [{"snaktype": "value", "property": "P248", "hash": "dbb8dd1efbe0158a5227213bd628eeac27a1da65", "datavalue": {"value": {"entity-type": "item", "numeric-id": 1531570, "id": "Q1531570"}, "type": "wikibase-entityid"}, "datatype": "wikibase-item"}], "P813": [{"snaktype": "value", "property": "P813", "hash": "c6c3ee3727b1c81cb30479c27617f21f90d555de", "datavalue": {"value": {"time": "+2015-05-26T00:00:00Z", "timezone": 0, "before": 0, "after": 0, "precision": 11, "calendarmodel": "http://www.wikidata.org/entity/Q1985727"}, "type": "time"}, "datatype": "time"}]}, "snaks-order": ["P248", "P813"]}]}], "P935": [{"mainsnak": {"snaktype": "value", "property": "P935", "hash": "a5f99d943c08bf1a99fc320d6c86552d9b0b4432", "datavalue": {"value": "Synchiropus splendidus", "type": "string"}, "datatype": "string"}, "type": "statement", "id": "Q77062$297A42F4-E49D-438B-AAD3-04167D0C62A7", "rank": "normal"}], "P3088": [{"mainsnak": {"snaktype": "value", "property": "P3088", "hash": "2a967c4e89da9994496b5f5211b06fc40086330f", "datavalue": {"value": "381504", "type": "string"}, "datatype": "external-id"}, "type": "statement", "id": "Q77062$2447CD87-8819-41CE-808F-1E58B4E32E03", "rank": "normal", "references": [{"hash": "64a7050f9c7d24592216b352805caa9f10193c21", "snaks": {"P248": [{"snaktype": "value", "property": "P248", "hash": "857d506ab5143e2c756ba632ced56a2f1e66c06f", "datavalue": {"value": {"entity-type": "item", "numeric-id": 26218155, "id": "Q26218155"}, "type": "wikibase-entityid"}, "datatype": "wikibase-item"}], "P813": [{"snaktype": "value", "property": "P813", "hash": "ed1ac4cf54e8ea379d0d8d079361eeafe1318bff", "datavalue": {"value": {"time": "+2016-08-23T00:00:00Z", "timezone": 0, "before": 0, "after": 0, "precision": 11, "calendarmodel": "http://www.wikidata.org/entity/Q1985727"}, "type": "time"}, "datatype": "time"}]}, "snaks-order": ["P248", "P813"]}]}], "P3151": [{"mainsnak": {"snaktype": "value", "property": "P3151", "hash": "0582653c5031cf5aac40d2435238f9e26619dfb9", "datavalue": {"value": "56072", "type": "string"}, "datatype": "external-id"}, "type": "statement", "id": "Q77062$5BCD3DED-D129-46FC-AB2D-A4AF6A034E01", "rank": "normal"}], "P3186": [{"mainsnak": {"snaktype": "value", "property": "P3186", "hash": "a0a777166bf04b793a8ab8bbaa2b1dbc98845ab9", "datavalue": {"value": "425843", "type": "string"}, "datatype": "external-id"}, "type": "statement", "id": "Q77062$17E5A0C1-B0F5-485E-8E9F-40926F952F71", "rank": "normal", "references": [{"hash": "5790a745e549ea7e4e6d7ca467148b544529ba96", "snaks": {"P248": [{"snaktype": "value", "property": "P248", "hash": "c897ca3efd1604ef7b80a14ac0d2b8d6849c0856", "datavalue": {"value": {"entity-type": "item", "numeric-id": 26936509, "id": "Q26936509"}, "type": "wikibase-entityid"}, "datatype": "wikibase-item"}], "P813": [{"snaktype": "value", "property": "P813", "hash": "555ca5385c445e4fd4762281d4873682eff2ce30", "datavalue": {"value": {"time": "+2016-09-24T00:00:00Z", "timezone": 0, "before": 0, "after": 0, "precision": 11, "calendarmodel": "http://www.wikidata.org/entity/Q1985727"}, "type": "time"}, "datatype": "time"}]}, "snaks-order": ["P248", "P813"]}, {"hash": "3edd37192f877cad0ff97acc3db56ef2cc83945b", "snaks": {"P248": [{"snaktype": "value", "property": "P248", "hash": "4f7c4fd187630ba8cbb174c2756113983df4ce82", "datavalue": {"value": {"entity-type": "item", "numeric-id": 45029859, "id": "Q45029859"}, "type": "wikibase-entityid"}, "datatype": "wikibase-item"}], "P813": [{"snaktype": "value", "property": "P813", "hash": "56b6aa0388c9a2711946589902bc195718bb0675", "datavalue": {"value": {"time": "+2017-12-26T00:00:00Z", "timezone": 0, "before": 0, "after": 0, "precision": 11, "calendarmodel": "http://www.wikidata.org/entity/Q1985727"}, "type": "time"}, "datatype": "time"}]}, "snaks-order": ["P248", "P813"]}, {"hash": "1318ed8ea451b84fe98461305665d8688603bab3", "snaks": {"P248": [{"snaktype": "value", "property": "P248", "hash": "0fbeeecce08896108ed797d8ec22c7c10a6015e2", "datavalue": {"value": {"entity-type": "item", "numeric-id": 45029998, "id": "Q45029998"}, "type": "wikibase-entityid"}, "datatype": "wikibase-item"}], "P813": [{"snaktype": "value", "property": "P813", "hash": "4bac1c0d2ffc45d91b51fc0881eb6bcc7916e854", "datavalue": {"value": {"time": "+2018-01-02T00:00:00Z", "timezone": 0, "before": 0, "after": 0, "precision": 11, "calendarmodel": "http://www.wikidata.org/entity/Q1985727"}, "type": "time"}, "datatype": "time"}]}, "snaks-order": ["P248", "P813"]}, {"hash": "6f761664a6f331d95bbaa1434447d82afd597a93", "snaks": {"P248": [{"snaktype": "value", "property": "P248", "hash": "6c09d1d89e83bd0dfa6c94e01d24a9a47489d83e", "datavalue": {"value": {"entity-type": "item", "numeric-id": 58035056, "id": "Q58035056"}, "type": "wikibase-entityid"}, "datatype": "wikibase-item"}], "P813": [{"snaktype": "value", "property": "P813", "hash": "03182012ca72fcd757b8a1fe05ba927cbe9ef374", "datavalue": {"value": {"time": "+2018-11-02T00:00:00Z", "timezone": 0, "before": 0, "after": 0, "precision": 11, "calendarmodel": "http://www.wikidata.org/entity/Q1985727"}, "type": "time"}, "datatype": "time"}]}, "snaks-order": ["P248", "P813"]}, {"hash": "867288cff15eec6d51ff8ed639d1be83f5202aa4", "snaks": {"P248": [{"snaktype": "value", "property": "P248", "hash": "7ccfcbb052595a87213ef0b38b218345754ac2c7", "datavalue": {"value": {"entity-type": "item", "numeric-id": 79844869, "id": "Q79844869"}, "type": "wikibase-entityid"}, "datatype": "wikibase-item"}], "P813": [{"snaktype": "value", "property": "P813", "hash": "754b72c09ef8897837b4389bfe28032989c39a6d", "datavalue": {"value": {"time": "+2019-12-31T00:00:00Z", "timezone": 0, "before": 0, "after": 0, "precision": 11, "calendarmodel": "http://www.wikidata.org/entity/Q1985727"}, "type": "time"}, "datatype": "time"}]}, "snaks-order": ["P248", "P813"]}, {"hash": "7cd84a60958326d32ead3c5144b77618028b5705", "snaks": {"P248": [{"snaktype": "value", "property": "P248", "hash": "d397541d01256ee3a57abbdfb5a864961982049f", "datavalue": {"value": {"entity-type": "item", "numeric-id": 104290728, "id": "Q104290728"}, "type": "wikibase-entityid"}, "datatype": "wikibase-item"}], "P813": [{"snaktype": "value", "property": "P813", "hash": "c673326694274755e8643428a748462e5b047d6a", "datavalue": {"value": {"time": "+2020-12-23T00:00:00Z", "timezone": 0, "before": 0, "after": 0, "precision": 11, "calendarmodel": "http://www.wikidata.org/entity/Q1985727"}, "type": "time"}, "datatype": "time"}]}, "snaks-order": ["P248", "P813"]}, {"hash": "8f362cf5bb158e9b659228a7e3b4d51fad4a01ab", "snaks": {"P248": [{"snaktype": "value", "property": "P248", "hash": "8493889b331a6a77688c103d0dfc5d839bb64548", "datavalue": {"value": {"entity-type": "item", "numeric-id": 110438362, "id": "Q110438362"}, "type": "wikibase-entityid"}, "datatype": "wikibase-item"}], "P813": [{"snaktype": "value", "property": "P813", "hash": "31c5874be90eb0e91ca018329f618257e81e4901", "datavalue": {"value": {"time": "+2022-01-20T00:00:00Z", "timezone": 0, "before": 0, "after": 0, "precision": 11, "calendarmodel": "http://www.wikidata.org/entity/Q1985727"}, "type": "time"}, "datatype": "time"}]}, "snaks-order": ["P248", "P813"]}, {"hash": "cfba94a07a77e29450dfbfbb1b004c8b9e031bd7", "snaks": {"P248": [{"snaktype": "value", "property": "P248", "hash": "48140273238fd3f1f42ee7474033f05df542b3d2", "datavalue": {"value": {"entity-type": "item", "numeric-id": 116008531, "id": "Q116008531"}, "type": "wikibase-entityid"}, "datatype": "wikibase-item"}], "P813": [{"snaktype": "value", "property": "P813", "hash": "07079106a960f0faf76d8b3b777755fd378514b2", "datavalue": {"value": {"time": "+2023-01-06T00:00:00Z", "timezone": 0, "before": 0, "after": 0, "precision": 11, "calendarmodel": "http://www.wikidata.org/entity/Q1985727"}, "type": "time"}, "datatype": "time"}]}, "snaks-order": ["P248", "P813"]}]}], "P1843": [{"mainsnak": {"snaktype": "value", "property": "P1843", "hash": "111d61c1748674c2cc4ea9c43caff364586d1859", "datavalue": {"value": {"text": "花斑連鰭", "language": "zh"}, "type": "monolingualtext"}, "datatype": "monolingualtext"}, "type": "statement", "id": "Q77062$B7D20E38-7686-436F-9E5A-3B97DBD70F54", "rank": "normal", "references": [{"hash": "004cdb6c519fe3a5a6aa973f5f29733eb7d0738c", "snaks": {"P248": [{"snaktype": "value", "property": "P248", "hash": "857d506ab5143e2c756ba632ced56a2f1e66c06f", "datavalue": {"value": {"entity-type": "item", "numeric-id": 26218155, "id": "Q26218155"}, "type": "wikibase-entityid"}, "datatype": "wikibase-item"}], "P3088": [{"snaktype": "value", "property": "P3088", "hash": "2a967c4e89da9994496b5f5211b06fc40086330f", "datavalue": {"value": "381504", "type": "string"}, "datatype": "external-id"}], "P813": [{"snaktype": "value", "property": "P813", "hash": "881cf86d7df499ff7761d91899c7aa65ffe7a7ac", "datavalue": {"value": {"time": "+2016-12-03T00:00:00Z", "timezone": 0, "before": 0, "after": 0, "precision": 11, "calendarmodel": "http://www.wikidata.org/entity/Q1985727"}, "type": "time"}, "datatype": "time"}]}, "snaks-order": ["P248", "P3088", "P813"]}]}, {"mainsnak": {"snaktype": "value", "property": "P1843", "hash": "59af7aa8bbab630a2c1cb081ac544e65f5f1ab69", "datavalue": {"value": {"text": "老鼠", "language": "zh"}, "type": "monolingualtext"}, "datatype": "monolingualtext"}, "type": "statement", "id": "Q77062$428D68BA-DEE3-447D-9957-38E0F1D0379E", "rank": "normal", "references": [{"hash": "004cdb6c519fe3a5a6aa973f5f29733eb7d0738c", "snaks": {"P248": [{"snaktype": "value", "property": "P248", "hash": "857d506ab5143e2c756ba632ced56a2f1e66c06f", "datavalue": {"value": {"entity-type": "item", "numeric-id": 26218155, "id": "Q26218155"}, "type": "wikibase-entityid"}, "datatype": "wikibase-item"}], "P3088": [{"snaktype": "value", "property": "P3088", "hash": "2a967c4e89da9994496b5f5211b06fc40086330f", "datavalue": {"value": "381504", "type": "string"}, "datatype": "external-id"}], "P813": [{"snaktype": "value", "property": "P813", "hash": "881cf86d7df499ff7761d91899c7aa65ffe7a7ac", "datavalue": {"value": {"time": "+2016-12-03T00:00:00Z", "timezone": 0, "before": 0, "after": 0, "precision": 11, "calendarmodel": "http://www.wikidata.org/entity/Q1985727"}, "type": "time"}, "datatype": "time"}]}, "snaks-order": ["P248", "P3088", "P813"]}]}, {"mainsnak": {"snaktype": "value", "property": "P1843", "hash": "7ee60082848311016d90fb69b8c3feb70bf81fd4", "datavalue": {"value": {"text": "狗圻", "language": "zh"}, "type": "monolingualtext"}, "datatype": "monolingualtext"}, "type": "statement", "id": "Q77062$DE99AE26-280E-4F8E-B6D3-CCAFA35FE642", "rank": "normal", "references": [{"hash": "004cdb6c519fe3a5a6aa973f5f29733eb7d0738c", "snaks": {"P248": [{"snaktype": "value", "property": "P248", "hash": "857d506ab5143e2c756ba632ced56a2f1e66c06f", "datavalue": {"value": {"entity-type": "item", "numeric-id": 26218155, "id": "Q26218155"}, "type": "wikibase-entityid"}, "datatype": "wikibase-item"}], "P3088": [{"snaktype": "value", "property": "P3088", "hash": "2a967c4e89da9994496b5f5211b06fc40086330f", "datavalue": {"value": "381504", "type": "string"}, "datatype": "external-id"}], "P813": [{"snaktype": "value", "property": "P813", "hash": "881cf86d7df499ff7761d91899c7aa65ffe7a7ac", "datavalue": {"value": {"time": "+2016-12-03T00:00:00Z", "timezone": 0, "before": 0, "after": 0, "precision": 11, "calendarmodel": "http://www.wikidata.org/entity/Q1985727"}, "type": "time"}, "datatype": "time"}]}, "snaks-order": ["P248", "P3088", "P813"]}]}, {"mainsnak": {"snaktype": "value", "property": "P1843", "hash": "a57b715a776672f17e4e9801239d3c9e0858d58f", "datavalue": {"value": {"text": "青蛙", "language": "zh"}, "type": "monolingualtext"}, "datatype": "monolingualtext"}, "type": "statement", "id": "Q77062$AC267945-D2CA-4B53-93EA-D3DBB73CA7C2", "rank": "normal", "references": [{"hash": "004cdb6c519fe3a5a6aa973f5f29733eb7d0738c", "snaks": {"P248": [{"snaktype": "value", "property": "P248", "hash": "857d506ab5143e2c756ba632ced56a2f1e66c06f", "datavalue": {"value": {"entity-type": "item", "numeric-id": 26218155, "id": "Q26218155"}, "type": "wikibase-entityid"}, "datatype": "wikibase-item"}], "P3088": [{"snaktype": "value", "property": "P3088", "hash": "2a967c4e89da9994496b5f5211b06fc40086330f", "datavalue": {"value": "381504", "type": "string"}, "datatype": "external-id"}], "P813": [{"snaktype": "value", "property": "P813", "hash": "881cf86d7df499ff7761d91899c7aa65ffe7a7ac", "datavalue": {"value": {"time": "+2016-12-03T00:00:00Z", "timezone": 0, "before": 0, "after": 0, "precision": 11, "calendarmodel": "http://www.wikidata.org/entity/Q1985727"}, "type": "time"}, "datatype": "time"}]}, "snaks-order": ["P248", "P3088", "P813"]}]}, {"mainsnak": {"snaktype": "value", "property": "P1843", "hash": "33e42afa8d87a6167b1a23a6dafdb59b2f14bf51", "datavalue": {"value": {"text": "花斑連鰭䲗", "language": "zh-tw"}, "type": "monolingualtext"}, "datatype": "monolingualtext"}, "type": "statement", "id": "Q77062$2EDB9D2F-6ED9-452E-B102-19C1F15C9F99", "rank": "normal"}, {"mainsnak": {"snaktype": "value", "property": "P1843", "hash": "c9b40b5d2dcfbdbf31583fd83ce18378c0d6c8c2", "datavalue": {"value": {"text": "pexe mandarín", "language": "ast"}, "type": "monolingualtext"}, "datatype": "monolingualtext"}, "type": "statement", "id": "Q77062$55640298-9F51-4D6B-9688-D0ECD4085BF4", "rank": "normal", "references": [{"hash": "25371c05886d508f0bd3b89319c1e188ec3c8883", "snaks": {"P854": [{"snaktype": "value", "property": "P854", "hash": "3b919fa0b95e83fae2c48274c12f675240ca702f", "datavalue": {"value": "http://www.sabencia.net/nomenclator.php", "type": "string"}, "datatype": "url"}]}, "snaks-order": ["P854"]}]}], "P4024": [{"mainsnak": {"snaktype": "value", "property": "P4024", "hash": "483193c3c6e10f28dc4504b3980a1ccc04a9ac4d", "datavalue": {"value": "Synchiropus_splendidus", "type": "string"}, "datatype": "external-id"}, "type": "statement", "id": "Q77062$AB9A878C-9E61-45F4-ACF4-8D32C6781FA2", "rank": "normal", "references": [{"hash": "d4bd87b862b12d99d26e86472d44f26858dee639", "snaks": {"P143": [{"snaktype": "value", "property": "P143", "hash": "f30cbd35620c4ea6d0633aaf0210a8916130469b", "datavalue": {"value": {"entity-type": "item", "numeric-id": 8447, "id": "Q8447"}, "type": "wikibase-entityid"}, "datatype": "wikibase-item"}]}, "snaks-order": ["P143"]}]}], "P4630": [{"mainsnak": {"snaktype": "value", "property": "P4630", "hash": "d0b8f6553fc178b49907c05e1400faf6c2d33508", "datavalue": {"value": "436", "type": "string"}, "datatype": "external-id"}, "type": "statement", "id": "Q77062$6FE4E0FD-84D6-46FE-885B-0E8E7EE45039", "rank": "normal"}], "P5055": [{"mainsnak": {"snaktype": "value", "property": "P5055", "hash": "807906455335c3c2f2c35a65d514d4d3c6e8421e", "datavalue": {"value": "10153138", "type": "string"}, "datatype": "external-id"}, "type": "statement", "id": "Q77062$D0C17481-C4C8-4704-A77A-4005B529B123", "rank": "normal", "references": [{"hash": "b1e6f8a0c71d7a3450f2a1a36bda2e9d83f804f6", "snaks": {"P248": [{"snaktype": "value", "property": "P248", "hash": "1e3ad3cb9e0170e28b7c7c335fba55cafa6ef789", "datavalue": {"value": {"entity-type": "item", "numeric-id": 51885189, "id": "Q51885189"}, "type": "wikibase-entityid"}, "datatype": "wikibase-item"}], "P813": [{"snaktype": "value", "property": "P813", "hash": "89772aa8125e4d3c992ba24755c521d25cc40b19", "datavalue": {"value": {"time": "+2018-05-30T00:00:00Z", "timezone": 0, "before": 0, "after": 0, "precision": 11, "calendarmodel": "http://www.wikidata.org/entity/Q1985727"}, "type": "time"}, "datatype": "time"}]}, "snaks-order": ["P248", "P813"]}]}], "P910": [{"mainsnak": {"snaktype": "value", "property": "P910", "hash": "c01c294d424a80f28a19f0d6d7b69a97974082c1", "datavalue": {"value": {"entity-type": "item", "numeric-id": 55324395, "id": "Q55324395"}, "type": "wikibase-entityid"}, "datatype": "wikibase-item"}, "type": "statement", "id": "Q77062$C521410F-B1B6-482A-A210-EC02646EBEB8", "rank": "normal"}], "P141": [{"mainsnak": {"snaktype": "value", "property": "P141", "hash": "f6158175530e6b445bf4165a2355180396d6765a", "datavalue": {"value": {"entity-type": "item", "numeric-id": 211005, "id": "Q211005"}, "type": "wikibase-entityid"}, "datatype": "wikibase-item"}, "type": "statement", "id": "Q77062$37EB51FC-F04D-4882-9FED-2E3A039BB832", "rank": "normal", "references": [{"hash": "9c38705148bbf9c76bedaf97a87c0f9372768eae", "snaks": {"P248": [{"snaktype": "value", "property": "P248", "hash": "4bf80ee227bb9925a1d31430fab2d8be4248a071", "datavalue": {"value": {"entity-type": "item", "numeric-id": 115962546, "id": "Q115962546"}, "type": "wikibase-entityid"}, "datatype": "wikibase-item"}], "P627": [{"snaktype": "value", "property": "P627", "hash": "54bdb0bfa513c871dcab88efe56c44867739a964", "datavalue": {"value": "141481104", "type": "string"}, "datatype": "external-id"}], "P813": [{"snaktype": "value", "property": "P813", "hash": "43d10596f7e11eaca13e261241c4676dfcb8232c", "datavalue": {"value": {"time": "+2023-01-04T00:00:00Z", "timezone": 0, "before": 0, "after": 0, "precision": 11, "calendarmodel": "http://www.wikidata.org/entity/Q1985727"}, "type": "time"}, "datatype": "time"}]}, "snaks-order": ["P248", "P627", "P813"]}]}], "P627": [{"mainsnak": {"snaktype": "value", "property": "P627", "hash": "54bdb0bfa513c871dcab88efe56c44867739a964", "datavalue": {"value": "141481104", "type": "string"}, "datatype": "external-id"}, "type": "statement", "id": "Q77062$C9E019BB-B5DD-4081-8AFD-1F68811C5B79", "rank": "normal", "references": [{"hash": "bd65a0e089be852cfcebf60c1c28af57c0b5a500", "snaks": {"P248": [{"snaktype": "value", "property": "P248", "hash": "ba14d022d7e0c8b74595e7b8aaa1bc2451dd806a", "datavalue": {"value": {"entity-type": "item", "numeric-id": 32059, "id": "Q32059"}, "type": "wikibase-entityid"}, "datatype": "wikibase-item"}], "P813": [{"snaktype": "value", "property": "P813", "hash": "8a4a246d2fcf49c5bd1c3622ede357ce1d638361", "datavalue": {"value": {"time": "+2020-01-07T00:00:00Z", "timezone": 0, "before": 0, "after": 0, "precision": 11, "calendarmodel": "http://www.wikidata.org/entity/Q1985727"}, "type": "time"}, "datatype": "time"}]}, "snaks-order": ["P248", "P813"]}]}], "P6366": [{"mainsnak": {"snaktype": "value", "property": "P6366", "hash": "27edec74de2e4742225a716cbbbce701b6804e47", "datavalue": {"value": "2778243689", "type": "string"}, "datatype": "external-id"}, "type": "statement", "id": "Q77062$86949D93-0FCC-47C8-90AC-AA2C88BDF501", "rank": "normal"}], "P3606": [{"mainsnak": {"snaktype": "value", "property": "P3606", "hash": "f7685222d5a9ae73089b2caa00a400e540ec59af", "datavalue": {"value": "47165", "type": "string"}, "datatype": "external-id"}, "type": "statement", "id": "Q77062$0465FA43-DA23-49A4-8C8E-E81B05A5B547", "rank": "normal", "references": [{"hash": "206b9bbe60c94626821a499dfdbabbac7b4e6310", "snaks": {"P248": [{"snaktype": "value", "property": "P248", "hash": "1c65e846218564f7d6b921ae8fc3ce0db9fa17c6", "datavalue": {"value": {"entity-type": "item", "numeric-id": 16934719, "id": "Q16934719"}, "type": "wikibase-entityid"}, "datatype": "wikibase-item"}], "P813": [{"snaktype": "value", "property": "P813", "hash": "0b47f71da3f9dbe7ab5a4b61d8c0399d2f0c2f82", "datavalue": {"value": {"time": "+2021-02-12T00:00:00Z", "timezone": 0, "before": 0, "after": 0, "precision": 11, "calendarmodel": "http://www.wikidata.org/entity/Q1985727"}, "type": "time"}, "datatype": "time"}]}, "snaks-order": ["P248", "P813"]}]}], "P527": [{"mainsnak": {"snaktype": "value", "property": "P527", "hash": "be0ba919ee337b147f2c41ba6574462935e2d104", "datavalue": {"value": {"entity-type": "item", "numeric-id": 504699, "id": "Q504699"}, "type": "wikibase-entityid"}, "datatype": "wikibase-item"}, "type": "statement", "id": "Q77062$2126294a-4770-03b2-62fe-bbca0ce8b251", "rank": "normal", "references": [{"hash": "84e17ad58d34c4ed8c0633ceee35e1f0c19c50ec", "snaks": {"P854": [{"snaktype": "value", "property": "P854", "hash": "0c87a6ab42045b4afcf0d5f881a5efe1871eae71", "datavalue": {"value": "https://zslpublications.onlinelibrary.wiley.com/doi/full/10.1111/jzo.12001", "type": "string"}, "datatype": "url"}], "P407": [{"snaktype": "value", "property": "P407", "hash": "daf1c4fcb58181b02dff9cc89deb084004ddae4b", "datavalue": {"value": {"entity-type": "item", "numeric-id": 1860, "id": "Q1860"}, "type": "wikibase-entityid"}, "datatype": "wikibase-item"}]}, "snaks-order": ["P854", "P407"]}]}, {"mainsnak": {"snaktype": "value", "property": "P527", "hash": "25b46e9967c7bfb99e72635e2631f2c49a107dd5", "datavalue": {"value": {"entity-type": "item", "numeric-id": 22329039, "id": "Q22329039"}, "type": "wikibase-entityid"}, "datatype": "wikibase-item"}, "type": "statement", "id": "Q77062$1e695ecd-47f1-6d11-4374-048b7f592a80", "rank": "normal", "references": [{"hash": "84e17ad58d34c4ed8c0633ceee35e1f0c19c50ec", "snaks": {"P854": [{"snaktype": "value", "property": "P854", "hash": "0c87a6ab42045b4afcf0d5f881a5efe1871eae71", "datavalue": {"value": "https://zslpublications.onlinelibrary.wiley.com/doi/full/10.1111/jzo.12001", "type": "string"}, "datatype": "url"}], "P407": [{"snaktype": "value", "property": "P407", "hash": "daf1c4fcb58181b02dff9cc89deb084004ddae4b", "datavalue": {"value": {"entity-type": "item", "numeric-id": 1860, "id": "Q1860"}, "type": "wikibase-entityid"}, "datatype": "wikibase-item"}]}, "snaks-order": ["P854", "P407"]}]}, {"mainsnak": {"snaktype": "value", "property": "P527", "hash": "2bcd3dae219736cc1d28217751bef92bd4f604a0", "datavalue": {"value": {"entity-type": "item", "numeric-id": 910979, "id": "Q910979"}, "type": "wikibase-entityid"}, "datatype": "wikibase-item"}, "type": "statement", "id": "Q77062$509a62e3-4db6-bec7-7b99-12e41ba06806", "rank": "normal", "references": [{"hash": "84e17ad58d34c4ed8c0633ceee35e1f0c19c50ec", "snaks": {"P854": [{"snaktype": "value", "property": "P854", "hash": "0c87a6ab42045b4afcf0d5f881a5efe1871eae71", "datavalue": {"value": "https://zslpublications.onlinelibrary.wiley.com/doi/full/10.1111/jzo.12001", "type": "string"}, "datatype": "url"}], "P407": [{"snaktype": "value", "property": "P407", "hash": "daf1c4fcb58181b02dff9cc89deb084004ddae4b", "datavalue": {"value": {"entity-type": "item", "numeric-id": 1860, "id": "Q1860"}, "type": "wikibase-entityid"}, "datatype": "wikibase-item"}]}, "snaks-order": ["P854", "P407"]}]}], "P462": [{"mainsnak": {"snaktype": "value", "property": "P462", "hash": "21c25d5d1bd2aacb5ea30ad25819f704a2d2adea", "datavalue": {"value": {"entity-type": "item", "numeric-id": 1088, "id": "Q1088"}, "type": "wikibase-entityid"}, "datatype": "wikibase-item"}, "type": "statement", "id": "Q77062$beda9754-4726-9506-5b04-557a443166fc", "rank": "normal"}], "P9876": [{"mainsnak": {"snaktype": "value", "property": "P9876", "hash": "0ba1a0222418efc9871882a883791064426b002e", "datavalue": {"value": "5296", "type": "string"}, "datatype": "external-id"}, "type": "statement", "id": "Q77062$2AE4AB4E-64AA-409F-990A-564EE68C817B", "rank": "normal"}], "P10585": [{"mainsnak": {"snaktype": "value", "property": "P10585", "hash": "fce8f23ccd526585fc67642a1b97fac69796de54", "datavalue": {"value": "7B8W2", "type": "string"}, "datatype": "external-id"}, "type": "statement", "id": "Q77062$68045A25-68DD-4263-9A97-AEC380043A73", "rank": "normal", "references": [{"hash": "acbf110eddba88f3fafa211d8ab0d53db381eebc", "snaks": {"P356": [{"snaktype": "value", "property": "P356", "hash": "693004d1410ff580ecf439e0a6af5513056e4960", "datavalue": {"value": "10.48580/DFPX", "type": "string"}, "datatype": "external-id"}]}, "snaks-order": ["P356"]}]}], "P9503": [{"mainsnak": {"snaktype": "value", "property": "P9503", "hash": "0c11e61c18519fe573ee8b39e0c9a680313a16d5", "datavalue": {"value": "28792", "type": "string"}, "datatype": "external-id"}, "type": "statement", "id": "Q77062$6A7E5D54-E678-44D5-904D-D9400CAE6F34", "rank": "normal"}], "P2892": [{"mainsnak": {"snaktype": "value", "property": "P2892", "hash": "999eb2861262c03c0a0430bbfa86a650749bcb4d", "datavalue": {"value": "C2758391", "type": "string"}, "datatype": "external-id"}, "type": "statement", "id": "Q77062$1422FE14-C7EE-4875-B566-99F053BD59BB", "rank": "normal", "references": [{"hash": "c6ec681dbce5124d2c86bcd84affe7c566c8dba6", "snaks": {"P887": [{"snaktype": "value", "property": "P887", "hash": "a0b7575579d620852cd869079ff98c2bbcc614b3", "datavalue": {"value": {"entity-type": "item", "numeric-id": 119459346, "id": "Q119459346"}, "type": "wikibase-entityid"}, "datatype": "wikibase-item"}], "P248": [{"snaktype": "value", "property": "P248", "hash": "0dffc9c217cd4550d6e1be4e56268ece7068efc2", "datavalue": {"value": {"entity-type": "item", "numeric-id": 118645236, "id": "Q118645236"}, "type": "wikibase-entityid"}, "datatype": "wikibase-item"}], "P813": [{"snaktype": "value", "property": "P813", "hash": "2c84d4d2819cd981f2be1b6733361587f949e9c7", "datavalue": {"value": {"time": "+2023-06-18T00:00:00Z", "timezone": 0, "before": 0, "after": 0, "precision": 11, "calendarmodel": "http://www.wikidata.org/entity/Q1985727"}, "type": "time"}, "datatype": "time"}]}, "snaks-order": ["P887", "P248", "P813"]}]}], "P6754": [{"mainsnak": {"snaktype": "value", "property": "P6754", "hash": "7001f33492bb5d919561538aef8438d2654f482f", "datavalue": {"value": "273264", "type": "string"}, "datatype": "external-id"}, "type": "statement", "id": "Q77062$32E89463-9525-41BB-995E-8A8B2607650A", "rank": "normal", "references": [{"hash": "147bc6e0e8cf9f480223fd78a57fb78bec6eb572", "snaks": {"P248": [{"snaktype": "value", "property": "P248", "hash": "aa2f092fb75896628abec256c3bc7d80f764a633", "datavalue": {"value": {"entity-type": "item", "numeric-id": 2013373, "id": "Q2013373"}, "type": "wikibase-entityid"}, "datatype": "wikibase-item"}]}, "snaks-order": ["P248"]}]}], "P4333": [{"mainsnak": {"snaktype": "value", "property": "P4333", "hash": "b07dbe6d11c873f605a6d598b92659c01c155820", "datavalue": {"value": "GCA_027744825.1", "type": "string"}, "datatype": "external-id"}, "type": "statement", "id": "Q77062$61195F5A-D615-4AEF-9FAD-45035985A88C", "rank": "normal"}], "P9157": [{"mainsnak": {"snaktype": "value", "property": "P9157", "hash": "2a05b4175be1acda92bbf7be1a469ec4c14b4ff8", "datavalue": {"value": "367540", "type": "string"}, "datatype": "external-id"}, "type": "statement", "id": "Q77062$4D1BF98B-3943-4A52-9376-1C1BBD8E1350", "rank": "normal", "references": [{"hash": "86b662879d38668f99cb8f4db4c0dff913c8824d", "snaks": {"P248": [{"snaktype": "value", "property": "P248", "hash": "993fd1273744a409e3ffcd9a63fbd49c27fd2824", "datavalue": {"value": {"entity-type": "item", "numeric-id": 124708476, "id": "Q124708476"}, "type": "wikibase-entityid"}, "datatype": "wikibase-item"}], "P813": [{"snaktype": "value", "property": "P813", "hash": "97df1ac3363eb970d1d85f437bcaf5d15676952d", "datavalue": {"value": {"time": "+2024-03-08T00:00:00Z", "timezone": 0, "before": 0, "after": 0, "precision": 11, "calendarmodel": "http://www.wikidata.org/entity/Q1985727"}, "type": "time"}, "datatype": "time"}]}, "snaks-order": ["P248", "P813"]}]}], "P12554": [{"mainsnak": {"snaktype": "value", "property": "P12554", "hash": "6733601b42cb924df901eb0d37104ae6bfabd28d", "datavalue": {"value": "Synchiropus+splendidus", "type": "string"}, "datatype": "external-id"}, "type": "statement", "id": "Q77062$0517C8FD-FC20-4BAA-808A-4A16DA29489A", "rank": "normal", "references": [{"hash": "a06cc0f86df889b618446dcbe0f7700371fd0ad7", "snaks": {"P248": [{"snaktype": "value", "property": "P248", "hash": "806e314d5327ccf7d6d2441bf9b4532e9ff61d4d", "datavalue": {"value": {"entity-type": "item", "numeric-id": 18379771, "id": "Q18379771"}, "type": "wikibase-entityid"}, "datatype": "wikibase-item"}]}, "snaks-order": ["P248"]}]}], "P12218": [{"mainsnak": {"snaktype": "value", "property": "P12218", "hash": "eba0bffe4e4aa3a6bd464ea12fd0cc5dc5f0bcd9", "datavalue": {"value": "t0033170", "type": "string"}, "datatype": "external-id"}, "type": "statement", "id": "Q77062$D1BEFD4B-1442-47D8-A4AC-499E49E68B9C", "rank": "normal"}], "P13591": [{"mainsnak": {"snaktype": "value", "property": "P13591", "hash": "e7526b58bcc053738b62d23e280357a9b88651f1", "datavalue": {"value": "concept/46458206-0fb4-49d8-82ea-833b457defbe", "type": "string"}, "datatype": "external-id"}, "type": "statement", "id": "Q77062$6FA543A6-4267-494B-B775-B5298AE34E5D", "rank": "normal"}], "P830": [{"mainsnak": {"snaktype": "value", "property": "P830", "hash": "8c6363360af9805ecfc7ba29786c42e44d362058", "datavalue": {"value": "46571393", "type": "string"}, "datatype": "external-id"}, "type": "statement", "id": "Q77062$ef48c0f4-4ea8-c1bd-d467-adc29618f778", "rank": "normal"}]}, "sitelinks": {"commonswiki": {"site": "commonswiki", "title": "Synchiropus splendidus", "badges": []}, "specieswiki": {"site": "specieswiki", "title": "Synchiropus splendidus", "badges": []}, "enwiki": {"site": "enwiki", "title": "Synchiropus splendidus", "badges": []}, "dewiki": {"site": "dewiki", "title": "Mandarinfisch", "badges": []}, "frwiki": {"site": "frwiki", "title": "Synchiropus splendidus", "badges": []}, "eswiki": {"site": "eswiki", "title": "Synchiropus splendidus", "badges": []}, "ruwiki": {"site": "ruwiki", "title": "Мандаринка (рыба)", "badges": []}, "itwiki": {"site": "itwiki", "title": "Synchiropus splendidus", "badges": []}, "jawiki": {"site": "jawiki", "title": "ニシキテグリ", "badges": []}, "nlwiki": {"site": "nlwiki", "title": "Blauwe mandarijnpitvis", "badges": []}, "plwiki": {"site": "plwiki", "title": "Mandaryn wspaniały", "badges": []}, "ptwiki": {"site": "ptwiki", "title": "Peixe-mandarim", "badges": []}, "zhwiki": {"site": "zhwiki", "title": "花斑連鰭䲗", "badges": []}, "svwiki": {"site": "svwiki", "title": "Mandarinfisk", "badges": []}, "fawiki": {"site": "fawiki", "title": "ماهی ماندارین", "badges": []}, "hewiki": {"site": "hewiki", "title": "מנדרין (דג)", "badges": []}, "trwiki": {"site": "trwiki", "title": "Mandalina balığı", "badges": []}, "huwiki": {"site": "huwiki", "title": "Mandarinhal", "badges": []}, "fiwiki": {"site": "fiwiki", "title": "Mandariinikala", "badges": []}, "viwiki": {"site": "viwiki", "title": "Cá trạng nguyên", "badges": []}, "ukwiki": {"site": "ukwiki", "title": "Мандаринка (риба)", "badges": []}, "kowiki": {"site": "kowiki", "title": "만다린피시", "badges": []}, "cawiki": {"site": "cawiki", "title": "Peix mandarí", "badges": []}, "cswiki": {"site": "cswiki", "title": "Vřeténka mandarín", "badges": []}, "idwiki": {"site": "idwiki", "title": "Ikan mandarin", "badges": []}, "bgwiki": {"site": "bgwiki", "title": "Риба мандарин", "badges": []}, "azwiki": {"site": "azwiki", "title": "Mandarinka", "badges": []}, "brwiki": {"site": "brwiki", "title": "Synchiropus splendidus", "badges": []}, "bswiki": {"site": "bswiki", "title": "Mandarinka", "badges": []}, "cebwiki": {"site": "cebwiki", "title": "Synchiropus splendidus", "badges": []}, "diqwiki": {"site": "diqwiki", "title": "Masey mandalina", "badges": []}, "eowiki": {"site": "eowiki", "title": "Mandarena fiŝo", "badges": []}, "euwiki": {"site": "euwiki", "title": "Synchiropus splendidus", "badges": []}, "glwiki": {"site": "glwiki", "title": "Peixe mandarín", "badges": []}, "hrwiki": {"site": "hrwiki", "title": "Mandarinska riba", "badges": []}, "hywiki": {"site": "hywiki", "title": "Մանդարինկա (ձուկ)", "badges": []}, "kywiki": {"site": "kywiki", "title": "Мандаринбалык", "badges": []}, "lbwiki": {"site": "lbwiki", "title": "Mandarinfësch", "badges": []}, "pnbwiki": {"site": "pnbwiki", "title": "مینڈارن مچھی", "badges": []}, "thwiki": {"site": "thwiki", "title": "ปลาแมนดาริน", "badges": []}, "arzwiki": {"site": "arzwiki", "title": "سمك ماندارين", "badges": []}, "afwiki": {"site": "afwiki", "title": "Mandarynvis", "badges": []}, "arwiki": {"site": "arwiki", "title": "سمك مندرين", "badges": []}}}}}