{"entities": {"Q66563232": {"pageid": 66162151, "ns": 0, "title": "Q66563232", "lastrevid": 2367694183, "modified": "2025-06-25T17:53:10Z", "type": "item", "id": "Q66563232", "labels": {"en": {"language": "en", "value": "organ system subdivision"}, "nn": {"language": "nn", "value": "del av organsystem"}, "eo": {"language": "eo", "value": "subdivido de organa sistemo"}, "hu": {"language": "hu", "value": "szervrendszeri felosztás"}, "ru": {"language": "ru", "value": "подразделение системы органов"}, "sl": {"language": "sl", "value": "delitev organskega sistema"}, "fr": {"language": "fr", "value": "subdivision d'un système organique"}, "uk": {"language": "uk", "value": "підвідділ системи органів"}, "ar": {"language": "ar", "value": "قسم فرعي من جهاز عضوي"}}, "descriptions": {}, "aliases": {"ar": [{"language": "ar", "value": "قسم فرعي من الجهاز العضوي"}]}, "claims": {"P1402": [{"mainsnak": {"snaktype": "value", "property": "P1402", "hash": "4a968cae36f4995375864280b5a6a51f804412e1", "datavalue": {"value": "67509", "type": "string"}, "datatype": "external-id"}, "type": "statement", "qualifiers": {"P1810": [{"snaktype": "value", "property": "P1810", "hash": "4fb11b68952ed0ca457209e8e08231ae6c53177d", "datavalue": {"value": "Organ system subdivision", "type": "string"}, "datatype": "string"}]}, "qualifiers-order": ["P1810"], "id": "Q66563232$16344490-12EA-4997-8401-4C709BEDF36E", "rank": "normal", "references": [{"hash": "3deb5336f981936e88d7ecccdfbb3519c4e7e149", "snaks": {"P248": [{"snaktype": "value", "property": "P248", "hash": "1b5fd2ff766b14dac1963a5e8745c7bdf17e9323", "datavalue": {"value": {"entity-type": "item", "numeric-id": 1406710, "id": "Q1406710"}, "type": "wikibase-entityid"}, "datatype": "wikibase-item"}], "P813": [{"snaktype": "value", "property": "P813", "hash": "d20c80df1d123bd85fffeee7c590024140499da9", "datavalue": {"value": {"time": "+2019-08-01T00:00:00Z", "timezone": 0, "before": 0, "after": 0, "precision": 11, "calendarmodel": "http://www.wikidata.org/entity/Q1985727"}, "type": "time"}, "datatype": "time"}]}, "snaks-order": ["P248", "P813"]}]}], "P279": [{"mainsnak": {"snaktype": "value", "property": "P279", "hash": "0805ba780bd1c8c8686ba71bc0c03818a4531a38", "datavalue": {"value": {"entity-type": "item", "numeric-id": 4936952, "id": "Q4936952"}, "type": "wikibase-entityid"}, "datatype": "wikibase-item"}, "type": "statement", "id": "Q66563232$2C67A80C-C8E6-458A-B244-F839E7D41988", "rank": "normal", "references": [{"hash": "ea9d3fde0a032770ae3ce6e12c7b97e21454a980", "snaks": {"P1402": [{"snaktype": "value", "property": "P1402", "hash": "4a968cae36f4995375864280b5a6a51f804412e1", "datavalue": {"value": "67509", "type": "string"}, "datatype": "external-id"}], "P248": [{"snaktype": "value", "property": "P248", "hash": "1b5fd2ff766b14dac1963a5e8745c7bdf17e9323", "datavalue": {"value": {"entity-type": "item", "numeric-id": 1406710, "id": "Q1406710"}, "type": "wikibase-entityid"}, "datatype": "wikibase-item"}], "P813": [{"snaktype": "value", "property": "P813", "hash": "d20c80df1d123bd85fffeee7c590024140499da9", "datavalue": {"value": {"time": "+2019-08-01T00:00:00Z", "timezone": 0, "before": 0, "after": 0, "precision": 11, "calendarmodel": "http://www.wikidata.org/entity/Q1985727"}, "type": "time"}, "datatype": "time"}]}, "snaks-order": ["P1402", "P248", "P813"]}]}, {"mainsnak": {"snaktype": "value", "property": "P279", "hash": "74c62ab9f3dbb3600ae4a6be2bfa3aabd10d4530", "datavalue": {"value": {"entity-type": "item", "numeric-id": 113137696, "id": "Q113137696"}, "type": "wikibase-entityid"}, "datatype": "wikibase-item"}, "type": "statement", "id": "Q66563232$839fdb42-42e1-6c60-8207-7e313ec9820a", "rank": "normal"}], "P31": [{"mainsnak": {"snaktype": "value", "property": "P31", "hash": "6dac6b3dac3463cdb0df5c365b46c9b622bc546f", "datavalue": {"value": {"entity-type": "item", "numeric-id": 103914748, "id": "Q103914748"}, "type": "wikibase-entityid"}, "datatype": "wikibase-item"}, "type": "statement", "id": "Q66563232$1e717494-4315-2cf3-83dc-fd848bc06bc0", "rank": "normal"}], "P1554": [{"mainsnak": {"snaktype": "value", "property": "P1554", "hash": "635710e67c4315f9652f72dea357f1fda02a83a6", "datavalue": {"value": "0011216", "type": "string"}, "datatype": "external-id"}, "type": "statement", "id": "Q66563232$0C73F1FC-3CFB-4D68-90A3-1216CF788E9C", "rank": "normal"}], "P2892": [{"mainsnak": {"snaktype": "value", "property": "P2892", "hash": "96fc6c16e1ce58424f5a61e23283cc5244dbe933", "datavalue": {"value": "C1744602", "type": "string"}, "datatype": "external-id"}, "type": "statement", "id": "Q66563232$DC0F4F47-8DA0-4AF0-9D02-7A6E56259B73", "rank": "normal", "references": [{"hash": "139accf5d4d45405aede70207560eccf92f0f97d", "snaks": {"P887": [{"snaktype": "value", "property": "P887", "hash": "c517fabf1daf7dc7136a88fa41437faea5cd29b9", "datavalue": {"value": {"entity-type": "item", "numeric-id": 119459341, "id": "Q119459341"}, "type": "wikibase-entityid"}, "datatype": "wikibase-item"}], "P248": [{"snaktype": "value", "property": "P248", "hash": "0dffc9c217cd4550d6e1be4e56268ece7068efc2", "datavalue": {"value": {"entity-type": "item", "numeric-id": 118645236, "id": "Q118645236"}, "type": "wikibase-entityid"}, "datatype": "wikibase-item"}], "P813": [{"snaktype": "value", "property": "P813", "hash": "ca3ad980cdd5625a07ee631ed3faf5fcc47a21b2", "datavalue": {"value": {"time": "+2023-06-15T00:00:00Z", "timezone": 0, "before": 0, "after": 0, "precision": 11, "calendarmodel": "http://www.wikidata.org/entity/Q1985727"}, "type": "time"}, "datatype": "time"}]}, "snaks-order": ["P887", "P248", "P813"]}]}]}, "sitelinks": {}}}}